{
    "space": {
        "EarthSky": "地球上空",
        "SolarInside": "内太阳系",
        "CeresSouth": "谷神星",
        "Ganymede": "木卫三",
        "GanymedeCave": "木卫三洞穴"
    },
    "spaceTask": {
        "YaSomewhere": "氩星某处",
        "StoneSea1": "氩星石海",
        "GanymedeCavern": "木卫三洞内"
    },
    "big": {
        "infected_area": "感染区"
    },
    "other": {
        "CavesDeep": "洞窟深处",
        "QiuYe": "丘野",
        "HuangMo2": "荒漠",
        "HuangMo3": "大荒漠",
        "XuWu1": "虚无之森",
        "KuRong": "枯荣镇",
        "LangXue": "狼穴",
        "Hospital": "时光洞",
        "FlySkyScene": "穹顶"
    },
    "task": {
        "GreenSomewhere": "绿岛某处",
        "YanJiuA": "研究室A",
        "HospitalUnder": "实验室地下",
        "MainUpland": "战斧高地",
        "FutureUpland": "战斧高地2053",
        "HanGuangSub": "寒光郊外",
        "QixiScene": "七夕天空",
        "GreenLand1": "绿岛外围",
        "RaysSea": "霞光海峡",
        "DaoTa": "倒塔村",
        "XingTop": "星谷之顶"
    },
    "infected_area": {
        "WoTu": "沃土镇",
        "YangMei": "杨梅岭",
        "XiaSha": "下沙",
        "FengWei": "凤尾洋",
        "XiChi": "西池",
        "BaiLu": "白鹭镇",
        "ShuiSheng": "水升村",
        "BaiZhang": "百丈道",
        "ZhuTou": "猪头洋",
        "ShuangTa": "双塔村",
        "BeiDou": "北斗城",
        "DongShan": "东山澳",
        "QingSha": "青纱镇",
        "QingMing": "清明岭",
        "NanTang": "南唐城",
        "YouLing": "幽灵谷",
        "XiFeng": "西峰",
        "LvSen": "绿森堡",
        "DuKu": "毒窟",
        "BaoLun": "宝伦镇",
        "LuYu": "炉屿",
        "BaWang": "霸王坡",
        "PingChuan": "平川",
        "BaiSha": "白沙村",
        "ShangSha": "上沙",
        "DongFeng": "东峰",
        "ZhongXin": "研究中心",
        "DiXia": "地下城",
        "HouJin": "后井",
        "ShaJiang": "沙江",
        "ShaMo": "沙漠中心",
        "XianQu": "先驱号",
        "FangZhouFirst": "方舟第1层",
        "FangZhouSecond": "方舟第2层",
        "FangZhouTop": "方舟顶层",
        "PrisonDoor": "监狱大门",
        "PrisonFirst": "监狱第1层",
        "PrisonDeep": "监狱深处",
        "PrisonExport": "监狱出口",
        "PrisonOutside": "监狱外围",
        "JungleOutside": "丛林外围",
        "JungleDeep": "丛林深处",
        "CavesEntrance": "洞窟入口",
        "CavesDeep": "洞窟深处",
        "QianYe": "千叶谷",
        "FuMu": "腐木岗",
        "GongMu": "公墓入口",
        "GuiWang": "鬼王墓",
        "BingKu": "冰窟",
        "BingKuDeep": "冰窟深处",
        "WuXue": "无雪干谷",
        "DongWu": "千年冻湖",
        "BuDong": "不冻湖",
        "PiaoMiao": "缥缈森林",
        "HanGuang1": "寒光入口",
        "HanGuang2": "寒光西城",
        "HanGuang3": "寒光中心",
        "HanGuang4": "寒光之巅",
        "HanGuang5": "寒光末路",
        "Hospital1": "实验室入口",
        "Hospital2": "实验室底层",
        "Hospital3": "实验室中层",
        "SkyScene": "天空顶",
        "Hospital5": "实验室顶层",
        "XingGu": "星谷",
        "XingPeak": "星谷之巅",
        "XiShan1": "绝壁窟",
        "XiShan2": "溪山西",
        "XiShan3": "溪山南",
        "XiShan4": "溪山顶",
        "XiShan5": "溪山东",
        "GreenIs1": "回头澳",
        "GreenIs2": "苍木道",
        "GreenIs3": "郁葱甸",
        "GreenIs4": "郁葱坪",
        "GreenTown1": "仙草镇入口"
    }
}